{
  "name": "Vinland Saga",
  "anilistId": 101348,
  "totalQuotes": 15,
  "totalCharacters": 7,
  "quotes": [
    {
      "id": "quote_1664_1755663518091",
      "character": "Thors",
      "quote": "You have no enemies. No one...Has any enemies. There is no one...That you should hurt"
    },
    {
      "id": "quote_1665_1755663518091",
      "character": "Askeladd",
      "quote": "A fight you can't win becomes an obsession"
    },
    {
      "id": "quote_1666_1755663518091",
      "character": "Canute",
      "quote": "The world...God's divine creation...Is so brimming with love...Yet there is no love in the hearts of men."
    },
    {
      "id": "quote_1667_1755663518091",
      "character": "Askeladd",
      "quote": "Only those who do their jobs on the battlefield get the rewards they desire. That's the life of a warrior."
    },
    {
      "id": "quote_1668_1755663518091",
      "character": "Askeladd",
      "quote": "You're young. Time is on your side. You'll grow up and I'll grow old. Someday you'll likely beat me. It's only natural. Even the strongest man must die."
    },
    {
      "id": "quote_1669_1755663518091",
      "character": "Thorkell",
      "quote": "I'd had fifteen years to think about him. And I realized that it wasn't a matter of the life or death of flesh. What's important to a warrior is the soul...And where it lies."
    },
    {
      "id": "quote_1670_1755663518091",
      "character": "Thorkell",
      "quote": "I love fighting, but even more than that, I hate losing! I only fight to win!!"
    },
    {
      "id": "quote_1671_1755663518091",
      "character": "Leif Ericson",
      "quote": "Not all warriors fight on the battlefield with a sword in hand. A sailor makes his living battling the sea"
    },
    {
      "id": "quote_1672_1755663518091",
      "character": "Father Willibald",
      "quote": "Let those who seek death find it."
    },
    {
      "id": "quote_1673_1755663518091",
      "character": "Thorkell",
      "quote": "Doesn't it ever get boring always being on the winning side?"
    },
    {
      "id": "quote_1674_1755663518091",
      "character": "Thors",
      "quote": "The only reason I must rely on this sword is because I am imperfect. A true warrior...Needs no sword"
    },
    {
      "id": "quote_1675_1755663518091",
      "character": "Askeladd",
      "quote": "A man, slave to gold, holds a whip...And beats the slave he bought with that gold as if to claim HE is the master. He just doesn't see it for himself. Every living human being is a slave to something"
    },
    {
      "id": "quote_1676_1755663518091",
      "character": "Father Willibald",
      "quote": "Love provides the worth of everything in the world. Without love...gold, silver, horses, and women...all are worthless."
    },
    {
      "id": "quote_1677_1755663518091",
      "character": "Ylva",
      "quote": "Well, if they're dead, then that's the end of it. Crying about it gets you nothing but an empty stomach"
    },
    {
      "id": "quote_1678_1755663518091",
      "character": "Canute",
      "quote": "Where in this world can a sane man be found? We're the same. We're all the same. None of us understands what it means to love all. Or the meaning of life...Or the meaning of death...Or the meaning of our own battles."
    }
  ]
}