{
  "name": "Kimi no Iru Machi",
  "anilistId": 17741,
  "totalQuotes": 5,
  "totalCharacters": 2,
  "quotes": [
    {
      "id": "quote_1418_1755681952053",
      "character": "Yuzuki Eba",
      "show": "Kimi no Iru Machi",
      "quote": "As long as I can be with you, I dont care what anyone says or how much I’m detested. As long as I can be with the one I love, that alone makes it okay. That’s what I longed for."
    },
    {
      "id": "quote_1419_1755681952053",
      "character": "Yuzuki Eba",
      "show": "Kimi no Iru Machi",
      "quote": "As long as you do not give up, nothing is over."
    },
    {
      "id": "quote_1420_1755681952053",
      "character": "Haruto Kirishima",
      "show": "Kimi no Iru Machi",
      "quote": "I have to be her place to belong. I need to be a steady, reliable man whom she can trust."
    },
    {
      "id": "quote_1421_1755681952053",
      "character": "Haruto Kirishima",
      "show": "Kimi no Iru Machi",
      "quote": "The more exciting it was to meet, the sadder it feels to say goodbye, right?"
    },
    {
      "id": "quote_1422_1755681952053",
      "character": "Haruto Kirishima",
      "show": "Kimi no Iru Machi",
      "quote": "Aren’t we family? Aren’t I like your family too? So it’s okay to cry if you’re having a hard time. Then I’ll do anything to help."
    }
  ]
}