{
  "name": "Yami no Matsuei",
  "anilistId": 553,
  "totalQuotes": 2,
  "totalCharacters": 1,
  "lastUpdated": "2025-08-20T10:38:27.462Z",
  "quotes": [
    {
      "id": "quote_83_1755686307462",
      "character": "Kazutaka Muraki",
      "show": "Yami no Matsuei",
      "quote": "Because I love you, I want to rip you apart. I want to pile corpses before you."
    },
    {
      "id": "quote_84_1755686307462",
      "character": "Kazutaka Muraki",
      "show": "Yami no Matsuei",
      "quote": "Humans are weak. For every cure found, another disease is uncovered. It's a game of chase."
    }
  ]
}